bank_statement_reader/__init__.py
bank_statement_reader/bookings.py
bank_statement_reader/cli.py
bank_statement_reader/exceptions.py
bank_statement_reader/statement_reader.py
bank_statement_reader/booking/__init__.py
bank_statement_reader/booking/booking_base.py
bank_statement_reader/booking/personal.py
bank_statement_reader-0.1.2.dist-info/AUTHORS.rst
bank_statement_reader-0.1.2.dist-info/LICENSE.txt
bank_statement_reader-0.1.2.dist-info/METADATA
bank_statement_reader-0.1.2.dist-info/WHEEL
bank_statement_reader-0.1.2.dist-info/entry_points.txt
bank_statement_reader-0.1.2.dist-info/top_level.txt
bank_statement_reader-0.1.2.dist-info/RECORD
