Metadata-Version: 2.1
Name: bank-statement-reader
Version: 0.1.2
Summary: Reading and converting PDF bank reports
Home-page: https://github.com/CarliJoy/GLS_account_statement_reader
Author: Carli* Freudenberg
Author-email: kound@posteo.de
License: MIT
Project-URL: Source, https://github.com/CarliJoy/GLS_account_statement_reader/
Project-URL: Changelog, https://github.com/CarliJoy/GLS_account_statement_reader/blob/master/CHANGELOG.rst
Project-URL: Tracker, https://github.com/CarliJoy/GLS_account_statement_reader/issues
Platform: any
Classifier: Development Status :: 4 - Beta
Classifier: Programming Language :: Python :: 3 :: Only
Classifier: Programming Language :: Python :: 3.6
Classifier: Programming Language :: Python :: 3.7
Classifier: Programming Language :: Python :: 3.8
Classifier: Programming Language :: Python :: 3.9
Classifier: Environment :: Console
Classifier: Intended Audience :: End Users/Desktop
Classifier: License :: OSI Approved :: MIT License
Classifier: Topic :: Office/Business :: Financial :: Accounting
Requires-Python: >=3.6
Requires-Dist: pdfminer.six (>=20201018)
Requires-Dist: natsort (<7.0,>=6.2.0)
Requires-Dist: schwifty (>=2020.11.0)
Requires-Dist: importlib-metadata ; python_version < "3.8"
Provides-Extra: testing
Requires-Dist: setuptools ; extra == 'testing'
Requires-Dist: pytest ; extra == 'testing'
Requires-Dist: pytest-cov ; extra == 'testing'
